init_mater_project/__init__.py
init_mater_project/main.py
init_mater_project/data/dimensions_hierarchy/.gitkeep
init_mater_project/data/input/.gitkeep
init_mater_project/data/raw/.gitkeep
init_mater_project/data/references/dimensions.json
init_mater_project/data/references/variables_dimensions.json
init_mater_project/examples/example_after_fhwa_reports_fleet_california.py
init_mater_project/examples/example_before_fhwa_reports_fleet_california.py
init_mater_project/examples/example_input_fhwa_reports_fleet_california.json
init_mater_project/examples/minimal_dimensions.json
init_mater_project/examples/minimal_dimensions_hierarchy.json
init_mater_project/examples/minimal_example.json
init_mater_project/examples/minimal_raw_after_example.py
init_mater_project/examples/minimal_raw_before_example.py
init_mater_project/examples/minimal_raw_example.csv
init_mater_project/examples/minimal_variables_dimensions.json
init_mater_project/outputs/.gitkeep
init_mater_project/src/__init__.py
init_mater_project/src/cli.py
init_mater_project/src/settings.py
init_mater_project/src/commands/__init__.py
init_mater_project/src/commands/build_dimensions.py
init_mater_project/src/commands/build_input_data.py
init_mater_project/src/commands/generate_data_script.py
init_mater_project/src/commands/list_simulation.py
init_mater_project/src/commands/map_dimensions.py
init_mater_project/src/commands/run.py
init_mater_project/src/lib/__init__.py
init_mater_project/src/lib/dimensions.py
init_mater_project/src/lib/validation.py
init_mater_project/static_files/.gitignore
init_mater_project/static_files/LICENSE
init_mater_project/static_files/config.toml
init_mater_project/templates/README.md.j2
init_mater_project/templates/pyproject.toml.j2
init_mater_project/transforms/datasets/.gitkeep
init_mater_project/transforms/templates/load_csv.py.j2
init_mater_project/transforms/templates/load_excel.py.j2
init_mater_project/transforms/templates/load_json.py.j2
init_mater_project-0.1.4.dist-info/METADATA
init_mater_project-0.1.4.dist-info/WHEEL
init_mater_project-0.1.4.dist-info/entry_points.txt
init_mater_project-0.1.4.dist-info/licenses/LICENSE
init_mater_project-0.1.4.dist-info/RECORD
