Metadata-Version: 2.4
Name: init-mater-project
Version: 0.1.4
Summary: A MATER project generator
Project-URL: Repository, https://gricad-gitlab.univ-grenoble-alpes.fr/isterre-dynamic-modeling/mater-project/init-mater-project
Project-URL: Documentation, https://isterre-dynamic-modeling.gricad-pages.univ-grenoble-alpes.fr/mater-project/init-mater-project
Author-email: Lauranne Sarribouette <lauranne.sarribouette@univ-grenoble-alpes.fr>, francois-verzier <francois.verzier@univ-grenoble-alpes.fr>
License:                    GNU LESSER GENERAL PUBLIC LICENSE
License-File: LICENSE
Keywords: cli,code-generator,mater,project-generator,research,scientific,simulation,template
Classifier: Development Status :: 4 - Beta
Classifier: Environment :: Console
Classifier: Intended Audience :: Science/Research
Classifier: License :: OSI Approved :: GNU Lesser General Public License v3 (LGPLv3)
Classifier: Operating System :: OS Independent
Classifier: Programming Language :: Python
Classifier: Programming Language :: Python :: 3.12
Classifier: Programming Language :: Python :: 3.13
Classifier: Topic :: Scientific/Engineering
Classifier: Topic :: Software Development :: Code Generators
Requires-Python: >=3.12
Requires-Dist: click>=8.2.1
Requires-Dist: email-validator>=2.2.0
Requires-Dist: jinja2>=3.1.6
Requires-Dist: mater>=0.12.3
Requires-Dist: pandas>=2.2.3
Requires-Dist: pydantic>=2.11.9
